odoo8_addon_medical-8.0.1.1.0.99.dev14-py2.7-nspkg.pth
odoo8_addon_medical-8.0.1.1.0.99.dev14.dist-info/DESCRIPTION.rst
odoo8_addon_medical-8.0.1.1.0.99.dev14.dist-info/METADATA
odoo8_addon_medical-8.0.1.1.0.99.dev14.dist-info/RECORD
odoo8_addon_medical-8.0.1.1.0.99.dev14.dist-info/WHEEL
odoo8_addon_medical-8.0.1.1.0.99.dev14.dist-info/metadata.json
odoo8_addon_medical-8.0.1.1.0.99.dev14.dist-info/namespace_packages.txt
odoo8_addon_medical-8.0.1.1.0.99.dev14.dist-info/top_level.txt
odoo_addons/medical/README.rst
odoo_addons/medical/__init__.py
odoo_addons/medical/__openerp__.py
odoo_addons/medical/medical_constants.py
odoo_addons/medical/data/medical_appointment_data.xml
odoo_addons/medical/i18n/pt_BR.po
odoo_addons/medical/i18n/sl.po
odoo_addons/medical/models/__init__.py
odoo_addons/medical/models/medical_appointment.py
odoo_addons/medical/models/medical_patient.py
odoo_addons/medical/models/medical_physician.py
odoo_addons/medical/models/medical_specialty.py
odoo_addons/medical/models/product_product.py
odoo_addons/medical/models/res_partner.py
odoo_addons/medical/security/ir.model.access.csv
odoo_addons/medical/security/medical_security.xml
odoo_addons/medical/static/description/icon.png
odoo_addons/medical/tests/__init__.py
odoo_addons/medical/tests/partners.yml
odoo_addons/medical/tests/patient.yml
odoo_addons/medical/tests/physician.yml
odoo_addons/medical/tests/physician_speciality.yml
odoo_addons/medical/tests/test_medical_patient.py
odoo_addons/medical/views/medical_appointment_view.xml
odoo_addons/medical/views/medical_menu.xml
odoo_addons/medical/views/medical_patient_view.xml
odoo_addons/medical/views/medical_physician_view.xml
odoo_addons/medical/views/medical_sequence.xml
odoo_addons/medical/views/medical_specialty_view.xml
odoo_addons/medical/views/product_product_view.xml
odoo_addons/medical/views/res_partner_view.xml
odoo_addons/medical/wizard/__init__.py
odoo_addons/medical/wizard/medical_physician_unavailable.py
odoo_addons/medical/wizard/medical_physician_unavailable_view.xml
